[
	{
	 "@" : "docs:employee_card",
	 "a": "rdfs:Class",
	 "ba:systemInformation": "$defaultRepresentation=swrc:lastName;$order=auth:login|docs:position|gost19:middleName|swrc:firstName|swrc:lastName|docs:unit|auth:credential|swrc:email|gost19:internal_phone|gost19:work_mobile|gost19:mobile|swrc:phone|docs:parentUnit",
	 "dc:creator": "zdb:person_de605422-4c48-4a0c-953d-fb50979ec667",
	 "dc:identifier": "docs:employee_card",
	 "dc:modified": "2013-04-24T18:11:41+00:00",
	 "docs:active": "true",
	 "docs:actual": "true",
	 "docs:kindOf": "user_template",
	 "link:exportPredicates": ["docs:parentUnit","docs:position","gost19:middleName","swrc:firstName","swrc:lastName"],
	 "rdfs:label": "Карточка пользователя@ru",
	 "rdfs:subClassOf": "docs:Document"	
	},
	{
	 "@" : "uo:rstr_docs:employee_card_swrc:email",
	 "a": "owl:Restriction",
	 "ba:code": "swrc:email",
	 "ba:description": "$isString;",
	 "dc:hasPart": "docs:employee_card",
	 "dc:identifier": "docs:employee_card",
	 "owl:allValuesFrom": "xsd:string",
	 "owl:maxCardinality": "1",
	 "owl:onProperty": "swrc:email",
	 "rdfs:label": "e-mail@ru"	
	},
	{
	 "@" : "uo:rstr_docs:employee_card_auth:login",
	 "a": "owl:Restriction",
	 "ba:code": "auth:login",
	 "ba:description": "$isString;",
	 "dc:hasPart": "docs:employee_card",
	 "dc:identifier": "docs:employee_card",
	 "owl:allValuesFrom": "xsd:string",
	 "owl:maxCardinality": "1",
	 "owl:minCardinality": "1",
	 "owl:onProperty": "auth:login",
	 "rdfs:label": "login@ru"	
	},
	{
	 "@" : "uo:rstr_docs:employee_card_gost19:internal_phone",
	 "a": "owl:Restriction",
	 "ba:code": "gost19:internal_phone",
	 "ba:description": "$isString;",
	 "dc:hasPart": "docs:employee_card",
	 "dc:identifier": "docs:employee_card",
	 "owl:allValuesFrom": "xsd:string",
	 "owl:maxCardinality": "1",
	 "owl:onProperty": "gost19:internal_phone",
	 "rdfs:label": "внутренний телефон@ru"	
	},
	{
	 "@" : "uo:rstr_docs:employee_card_gost19:middleName",
	 "a": "owl:Restriction",
	 "ba:code": "gost19:middleName",
	 "ba:description": "$isString;",
	 "dc:hasPart": "docs:employee_card",
	 "dc:identifier": "docs:employee_card",
	 "owl:allValuesFrom": "xsd:string",
	 "owl:maxCardinality": "1",
	 "owl:onProperty": "gost19:middleName",
	 "rdfs:label": "отчество@ru"	
	},
	{
	 "@" : "uo:rstr_docs:employee_card_auth:credential",
	 "a": "owl:Restriction",
	 "ba:code": "auth:credential",
	 "ba:description": "$isString;",
	 "dc:hasPart": "docs:employee_card",
	 "dc:identifier": "docs:employee_card",
	 "owl:allValuesFrom": "xsd:string",
	 "owl:maxCardinality": "1",
	 "owl:onProperty": "auth:credential",
	 "rdfs:label": "пароль@ru"	
	},
	{
	 "@" : "uo:rstr_docs:employee_card_gost19:work_mobile",
	 "a": "owl:Restriction",
	 "ba:code": "gost19:work_mobile",
	 "ba:description": "$isString;",
	 "dc:hasPart": "docs:employee_card",
	 "dc:identifier": "docs:employee_card",
	 "owl:allValuesFrom": "xsd:string",
	 "owl:maxCardinality": "1",
	 "owl:onProperty": "gost19:work_mobile",
	 "rdfs:label": "рабочий сотовый@ru"	
	},
	{
	 "@" : "uo:rstr_docs:employee_card_docs:parentUnit",
	 "a": "owl:Restriction",
	 "ba:code": "docs:parentUnit",
	 "ba:organizationTag": "department",
	 "dc:hasPart": "docs:employee_card",
	 "dc:identifier": "docs:employee_card",
	 "docs:importPredicate": "swrc:name",
	 "owl:allValuesFrom": "swrc:Department",
	 "owl:maxCardinality": "1",
	 "owl:minCardinality": "1",
	 "owl:onProperty": "docs:parentUnit",
	 "rdfs:label": "ссылка на вышестоящую орг еденицу@ru"	
	},
	{
	 "@" : "uo:rstr_docs:employee_card_swrc:lastName",
	 "a": "owl:Restriction",
	 "ba:code": "swrc:lastName",
	 "ba:description": "$isString;",
	 "dc:hasPart": "docs:employee_card",
	 "dc:identifier": "docs:employee_card",
	 "owl:allValuesFrom": "xsd:string",
	 "owl:maxCardinality": "1",
	 "owl:onProperty": "swrc:lastName",
	 "rdfs:label": "фамилия@ru"	
	},
	{
	 "@" : "uo:rstr_docs:employee_card_gost19:mobile",
	 "a": "owl:Restriction",
	 "ba:code": "gost19:mobile",
	 "ba:description": "$isString;",
	 "dc:hasPart": "docs:employee_card",
	 "dc:identifier": "docs:employee_card",
	 "owl:allValuesFrom": "xsd:string",
	 "owl:maxCardinality": "1",
	 "owl:onProperty": "gost19:mobile",
	 "rdfs:label": "сотовый@ru"	
	},
	{
	 "@" : "uo:rstr_docs:employee_card_docs:unit",
	 "a": "owl:Restriction",
	 "ba:code": "docs:unit",
	 "ba:description": "$isString;",
	 "dc:hasPart": "docs:employee_card",
	 "dc:identifier": "docs:employee_card",
	 "owl:allValuesFrom": "xsd:string",
	 "owl:maxCardinality": "1",
	 "owl:onProperty": "docs:unit",
	 "rdfs:label": "субьект@ru"	
	},
	{
	 "@" : "uo:rstr_docs:employee_card_swrc:phone",
	 "a": "owl:Restriction",
	 "ba:code": "swrc:phone",
	 "ba:description": "$isString;",
	 "dc:hasPart": "docs:employee_card",
	 "dc:identifier": "docs:employee_card",
	 "owl:allValuesFrom": "xsd:string",
	 "owl:maxCardinality": "1",
	 "owl:onProperty": "swrc:phone",
	 "rdfs:label": "телефон@ru"	
	},
	{
	 "@" : "uo:rstr_docs:employee_card_uo:$comment",
	 "a": "owl:Restriction",
	 "ba:code": "$comment",
	 "dc:hasPart": "docs:employee_card",
	 "dc:identifier": "docs:employee_card",
	 "owl:allValuesFrom": "xsd:string",
	 "owl:maxCardinality": "1",
	 "owl:onProperty": "uo:$comment",
	 "rdfs:label": "$comment@ru"	
	},
	{
	 "@" : "uo:rstr_docs:employee_card_docs:position",
	 "a": "owl:Restriction",
	 "ba:code": "docs:position",
	 "ba:description": "$isString;",
	 "dc:hasPart": "docs:employee_card",
	 "dc:identifier": "docs:employee_card",
	 "owl:allValuesFrom": "xsd:string",
	 "owl:maxCardinality": "1",
	 "owl:onProperty": "docs:position",
	 "rdfs:label": "должность@ru"	
	},
	{
	 "@" : "uo:rstr_docs:employee_card_swrc:firstName",
	 "a": "owl:Restriction",
	 "ba:code": "swrc:firstName",
	 "ba:description": "$isString;",
	 "dc:hasPart": "docs:employee_card",
	 "dc:identifier": "docs:employee_card",
	 "owl:allValuesFrom": "xsd:string",
	 "owl:maxCardinality": "1",
	 "owl:onProperty": "swrc:firstName",
	 "rdfs:label": "Имя@ru"	
	}
]
